setup.py
emml_prob_func/Binomialdistribution.py
emml_prob_func/Gaussiandistribution.py
emml_prob_func/Generaldistribution.py
emml_prob_func/__init__.py
emml_prob_func.egg-info/PKG-INFO
emml_prob_func.egg-info/SOURCES.txt
emml_prob_func.egg-info/dependency_links.txt
emml_prob_func.egg-info/not-zip-safe
emml_prob_func.egg-info/top_level.txt