Metadata-Version: 1.0
Name: emml-prob-func
Version: 1.0
Summary: Gaussian distributions
Home-page: UNKNOWN
Author: Emmanuel Fiagbedzi
Author-email: ekfiagbedzi@gmail.com
License: UNKNOWN
Platform: UNKNOWN
